PythonCoordinates/__init__.py
PythonCoordinates/conversions/GpsTime.py
PythonCoordinates/conversions/Physics.py
PythonCoordinates/conversions/__init__.py
PythonCoordinates/conversions/measurement_resolution.py
PythonCoordinates/coordinates/__init__.py
PythonCoordinates/coordinates/coordinate_representations.py
PythonCoordinates/coordinates/geospatial_coordinates.py
PythonCoordinates/coordinates/track.py
PythonCoordinates/linear_algebra/MatrixRotations.py
PythonCoordinates/linear_algebra/__init__.py
PythonCoordinates/linear_algebra/test_MatrixRotations.py
PythonCoordinates/measurables/Measurable.py
PythonCoordinates/measurables/__init__.py
PythonCoordinates/measurables/physical_quantities.py
PythonCoordinates-0.9.4.dist-info/METADATA
PythonCoordinates-0.9.4.dist-info/WHEEL
PythonCoordinates-0.9.4.dist-info/top_level.txt
PythonCoordinates-0.9.4.dist-info/RECORD
