Metadata-Version: 2.1
Name: PythonCoordinates
Version: 0.9.4
Summary: A collection of classes for representing the physical measurable quantities and the methods to locate them
Home-page: https://gitlab.com/frankmobley/physical_quantities_coordinates
Author: Dr. Frank Mobley
Author-email: frank.mobley.1@afrl.af.mil
Requires-Dist: numpy
Requires-Dist: scipy
Requires-Dist: geojson
